LICENSE
README.md
rtmo_ort/__init__.py
rtmo_ort/cli.py
rtmo_ort/estimator.py
rtmo_ort-0.1.0.post1.dist-info/METADATA
rtmo_ort-0.1.0.post1.dist-info/WHEEL
rtmo_ort-0.1.0.post1.dist-info/entry_points.txt
rtmo_ort-0.1.0.post1.dist-info/licenses/LICENSE
rtmo_ort-0.1.0.post1.dist-info/RECORD
