Metadata-Version: 2.4
Name: rtmo-ort
Version: 0.1.0.post1
Summary: RTMO pose estimation with pure ONNX Runtime (tiny class + CLI).
Project-URL: Homepage, https://github.com/namas191297/rtmo-ort
Project-URL: Issues, https://github.com/namas191297/rtmo-ort/issues
Author: Namas
License-File: LICENSE
Keywords: RTMO,keypoints,mmpose,onnxruntime,pose,realtime
Requires-Python: >=3.8
Requires-Dist: numpy
Requires-Dist: opencv-python
Provides-Extra: cpu
Requires-Dist: onnxruntime; extra == 'cpu'
Provides-Extra: gpu
Requires-Dist: onnxruntime-gpu; extra == 'gpu'
